{
  "@pnp/generator-spfx": {
    "framework": "react",
    "pnpFramework": "reactjs.plus",
    "pnp-libraries": [
      "rush@3.7"
    ],
    "pnp-ci": "no-devops",
    "pnp-vetting": [],
    "spfxenv": "spo",
    "pnp-testing": []
  },
  "@microsoft/generator-sharepoint": {
    "environment": "spo",
    "framework": "react",
    "isCreatingSolution": true,
    "version": "1.10.0",
    "libraryName": "pn-p-property-field-collection-data",
    "libraryId": "7212fc42-9be2-41ac-87a8-6d90d90eb55d",
    "packageManager": "npm",
    "isDomainIsolated": false,
    "componentType": "webpart"
  }
}